ocspchecker/__init__.py
ocspchecker/__main__.py
ocspchecker/ocspchecker.py
ocspchecker/utils/__init__.py
ocspchecker/utils/http_proxy_connect.py
ocsp_checker-2.0.0.dist-info/LICENSE.txt
ocsp_checker-2.0.0.dist-info/METADATA
ocsp_checker-2.0.0.dist-info/WHEEL
ocsp_checker-2.0.0.dist-info/entry_points.txt
ocsp_checker-2.0.0.dist-info/top_level.txt
ocsp_checker-2.0.0.dist-info/RECORD
