Metadata-Version: 2.2
Name: ocsp-checker
Version: 2.0.0
Summary: Library used to check the OCSP revocation status for a x509 digital certificate.
Author-email: Joe Gatt <gattjoseph@hotmail.com>
License:  Copyright (c) 2019-present, MetLife Services and Solutions, LLC
Project-URL: homepage, https://github.com/gattjoe/OCSPChecker
Project-URL: documentation, https://github.com/gattjoe/OCSPChecker/blob/master/README.md
Project-URL: repository, https://github.com/gattjoe/OCSPChecker
Project-URL: changelog, https://github.com/gattjoe/OCSPChecker/blob/master/CHANGELOG.md
Keywords: ssl, tls, ocsp, python, security
Classifier: License :: OSI Approved :: Apache Software License
Classifier: Programming Language :: Python :: 3
Classifier: Programming Language :: Python :: 3.8
Classifier: Programming Language :: Python :: 3.9
Classifier: Programming Language :: Python :: 3.10
Classifier: Programming Language :: Python :: 3.11
Classifier: Programming Language :: Python :: 3.12
Classifier: Programming Language :: Python :: 3.13
Requires-Python: >=3.9
License-File: LICENSE.txt
Requires-Dist: cryptography>=44.0
Requires-Dist: nassl>=5.3
Requires-Dist: certifi
